econkit/__init__.py
econkit/econometrics.py
econkit/finance.py
econkit/version.py
econkit-0.5.8.dist-info/LICENSE
econkit-0.5.8.dist-info/METADATA
econkit-0.5.8.dist-info/WHEEL
econkit-0.5.8.dist-info/top_level.txt
econkit-0.5.8.dist-info/RECORD
